MANIFEST.in
README.rst
requirements.txt
setup.cfg
setup.py
pyIsis_ReadOnly/VERSION
pyIsis_ReadOnly/__init__.py
pyIsis_ReadOnly/connection.py
pyIsis_ReadOnly/filesystem.py
pyIsis_ReadOnly/utils.py
pyIsis_ReadOnly.egg-info/PKG-INFO
pyIsis_ReadOnly.egg-info/SOURCES.txt
pyIsis_ReadOnly.egg-info/dependency_links.txt
pyIsis_ReadOnly.egg-info/not-zip-safe
pyIsis_ReadOnly.egg-info/requires.txt
pyIsis_ReadOnly.egg-info/top_level.txt