Metadata-Version: 1.1
Name: pyIsis-ReadOnly
Version: 0.2.2
Summary: Python wrapper for Avid Isis Client Management Console
Home-page: http://github.com/pixelrebel/pyIsis_ReadOnly
Author: Jamie Evans
Author-email: github@pixelrebel.com
License: MIT
Download-URL: https://github.com/pixelrebel/pyIsis_ReadOnly/tarball/0.2.2
Keywords: avid isis client mount workspace
Platform: UNKNOWN
Classifier: Development Status :: 4 - Beta
Classifier: Environment :: MacOS X
Classifier: Intended Audience :: Information Technology
Classifier: Intended Audience :: System Administrators
Classifier: License :: OSI Approved :: MIT License
Classifier: Natural Language :: English
Classifier: Programming Language :: Python
Classifier: Topic :: System :: Systems Administration
Classifier: Topic :: System :: Filesystems
Classifier: Topic :: Utilities
